dask_bigquery/__init__.py
dask_bigquery/core.py
dask_bigquery/tests/__init__.py
dask_bigquery/tests/test_core.py
dask_bigquery-2024.7.0.dist-info/LICENSE
dask_bigquery-2024.7.0.dist-info/METADATA
dask_bigquery-2024.7.0.dist-info/WHEEL
dask_bigquery-2024.7.0.dist-info/top_level.txt
dask_bigquery-2024.7.0.dist-info/RECORD
