Metadata-Version: 2.1
Name: dask-bigquery
Version: 2024.7.0
Summary: Dask + BigQuery integration
License: BSD
Requires-Python: >=3.9
License-File: LICENSE
Requires-Dist: dask >=2024.3.0
Requires-Dist: gcsfs
Requires-Dist: google-cloud-bigquery >=2.11.0
Requires-Dist: google-cloud-bigquery-storage
Requires-Dist: pandas
Requires-Dist: pyarrow
Provides-Extra: test
Requires-Dist: pytest ; extra == 'test'
Requires-Dist: distributed ; extra == 'test'
Requires-Dist: google-auth >=1.30.0 ; extra == 'test'
